resumablesha256/_sha256_ext.abi3.so
resumablesha256/__init__.py
resumablesha256-1.0.dist-info/WHEEL
resumablesha256-1.0.dist-info/RECORD
resumablesha256-1.0.dist-info/LICENSE.txt
resumablesha256-1.0.dist-info/top_level.txt
resumablesha256-1.0.dist-info/METADATA
