Metadata-Version: 2.1
Name: resumablesha256
Version: 1.0
Summary: A resumable SHA-256 hasher using B-Con's sha256 C implementation
Author: Luke Moore
License: Unlicense
Project-URL: Homepage, https://github.com/luke-moore/resumablesha256/
Classifier: Programming Language :: Python :: 3
Classifier: Operating System :: OS Independent
Requires-Python: >=3.6
License-File: LICENSE.txt
